invenio_audit_logs/__init__.py
invenio_audit_logs/config.py
invenio_audit_logs/ext.py
invenio_audit_logs/proxies.py
invenio_audit_logs/views.py
invenio_audit_logs/alembic/1743073617_create_audit_logs_branch.py
invenio_audit_logs/alembic/1743073720_create_audit_logs_table.py
invenio_audit_logs/alembic/42fa8d3bbc0c_change_datetime_types.py
invenio_audit_logs/records/__init__.py
invenio_audit_logs/records/api.py
invenio_audit_logs/records/models.py
invenio_audit_logs/records/mappings/__init__.py
invenio_audit_logs/records/mappings/templates/__init__.py
invenio_audit_logs/records/mappings/templates/os-v1/__init__.py
invenio_audit_logs/records/mappings/templates/os-v1/auditlogs/datastream-auditlog-v1.0.0.json
invenio_audit_logs/records/mappings/templates/os-v2/__init__.py
invenio_audit_logs/records/mappings/templates/os-v2/auditlogs/datastream-auditlog-v1.0.0.json
invenio_audit_logs/records/systemfields/__init__.py
invenio_audit_logs/records/systemfields/action.py
invenio_audit_logs/resources/__init__.py
invenio_audit_logs/resources/config.py
invenio_audit_logs/resources/resource.py
invenio_audit_logs/services/__init__.py
invenio_audit_logs/services/action.py
invenio_audit_logs/services/config.py
invenio_audit_logs/services/permissions.py
invenio_audit_logs/services/results.py
invenio_audit_logs/services/schema.py
invenio_audit_logs/services/service.py
invenio_audit_logs/services/uow.py
invenio_audit_logs-1.0.0.dist-info/licenses/AUTHORS.rst
invenio_audit_logs-1.0.0.dist-info/licenses/LICENSE
invenio_audit_logs-1.0.0.dist-info/METADATA
invenio_audit_logs-1.0.0.dist-info/WHEEL
invenio_audit_logs-1.0.0.dist-info/entry_points.txt
invenio_audit_logs-1.0.0.dist-info/top_level.txt
invenio_audit_logs-1.0.0.dist-info/RECORD
