Metadata-Version: 2.4
Name: invenio-audit-logs
Version: 1.0.0
Summary: Module providing audit logging features for Invenio.
Home-page: https://github.com/inveniosoftware/invenio-audit-logs
Author: CERN
Author-email: info@inveniosoftware.org
License: MIT
Keywords: invenio TODO
Platform: any
Classifier: Development Status :: 1 - Planning
Requires-Python: >=3.8
License-File: LICENSE
License-File: AUTHORS.rst
Requires-Dist: invenio-base<3.0.0,>=2.3.0
Requires-Dist: invenio-i18n<4.0.0,>=3.0.0
Requires-Dist: invenio-indexer<5.0.0,>=4.0.0
Requires-Dist: invenio-records-resources<10.0.0,>=9.0.0
Requires-Dist: invenio-administration<6.0.0,>=5.0.0
Requires-Dist: invenio-accounts<8.0.0,>=7.0.0
Provides-Extra: tests
Requires-Dist: pytest-black>=0.6.0; extra == "tests"
Requires-Dist: pytest-invenio<5.0.0,>=4.0.0; extra == "tests"
Requires-Dist: invenio-db<3.0.0,>=2.2.0; extra == "tests"
Requires-Dist: invenio-app<4.0.0,>=3.0.0; extra == "tests"
Requires-Dist: invenio-indexer<5.0.0,>=4.0.0; extra == "tests"
Requires-Dist: Sphinx>=4.5.0; extra == "tests"
Provides-Extra: elasticsearch7
Requires-Dist: invenio-search[elasticsearch7]<4.0.0,>=3.0.0; extra == "elasticsearch7"
Provides-Extra: opensearch1
Requires-Dist: invenio-search[opensearch1]<4.0.0,>=3.0.0; extra == "opensearch1"
Provides-Extra: opensearch2
Requires-Dist: invenio-search[opensearch2]<4.0.0,>=3.0.0; extra == "opensearch2"
Dynamic: license-file
